labelspark/__init__.py
labelspark/add_json_answers_to_dictionary.py
labelspark/api_key.py
labelspark/bronze_to_silver.py
labelspark/client.py
labelspark/connector.py
labelspark/constants.py
labelspark/create_dataset.py
labelspark/create_labelbox_dataset.py
labelspark/dataframe_schema_enrichment.py
labelspark/dictionary_collector.py
labelspark/flatten_bronze_table.py
labelspark/get_annotations.py
labelspark/get_videoframe_annotations.py
labelspark/is_json.py
labelspark/jsonToDataFrame.py
labelspark/spark_schema_to_string.py
labelspark/update_metadata.py
labelspark/uploader.py
labelspark-0.8.1.dist-info/LICENSE
labelspark-0.8.1.dist-info/METADATA
labelspark-0.8.1.dist-info/WHEEL
labelspark-0.8.1.dist-info/top_level.txt
labelspark-0.8.1.dist-info/RECORD
