Metadata-Version: 2.1
Name: labelspark
Version: 0.8.1
Summary: Labelbox Connector for Databricks
Home-page: https://github.com/Labelbox/LabelSpark.git
Author: Labelbox
Author-email: raphael@labelbox.com
License-File: LICENSE
Requires-Dist: labelbox[data]
Requires-Dist: pyspark
Requires-Dist: packaging
Requires-Dist: labelbase
Requires-Dist: delta-spark
Provides-Extra: dev
Requires-Dist: pylint ; extra == 'dev'
